senaite.core.listing-1.2.0-py2.7-nspkg.pth
senaite/core/listing/__init__.py
senaite/core/listing/ajax.py
senaite/core/listing/configure.zcml
senaite/core/listing/decorators.py
senaite/core/listing/interfaces.py
senaite/core/listing/setuphandlers.py
senaite/core/listing/utils.py
senaite/core/listing/view.py
senaite/core/listing/profiles/default/cssregistry.xml
senaite/core/listing/profiles/default/jsregistry.xml
senaite/core/listing/profiles/default/metadata.xml
senaite/core/listing/profiles/default/senaite.core.listing.txt
senaite/core/listing/profiles/uninstall/cssregistry.xml
senaite/core/listing/profiles/uninstall/jsregistry.xml
senaite/core/listing/profiles/uninstall/metadata.xml
senaite/core/listing/profiles/uninstall/senaite.core.listing.uninstall.txt
senaite/core/listing/static/js/senaite.core.listing.js
senaite/core/listing/templates/contents_table.pt
senaite/core/listing/templates/listing.pt
senaite/core/listing/tests/__init__.py
senaite/core/listing/tests/base.py
senaite/core/listing/tests/test_doctests.py
senaite/core/listing/tests/test_setup.py
senaite.core.listing-1.2.0.dist-info/LICENSE
senaite.core.listing-1.2.0.dist-info/METADATA
senaite.core.listing-1.2.0.dist-info/WHEEL
senaite.core.listing-1.2.0.dist-info/entry_points.txt
senaite.core.listing-1.2.0.dist-info/namespace_packages.txt
senaite.core.listing-1.2.0.dist-info/top_level.txt
senaite.core.listing-1.2.0.dist-info/RECORD
