Metadata-Version: 2.1
Name: senaite.core.listing
Version: 1.2.0
Summary: ReactJS powered listing tables for SENAITE LIMS
Home-page: https://github.com/senaite/senaite.core.listing
Author: SENAITE Foundation
Author-email: hello@senaite.com
License: GPLv2
Keywords: senaite,lims,opensource,reactjs
Platform: UNKNOWN
Classifier: Programming Language :: Python
Classifier: Framework :: Plone
Classifier: Framework :: Zope2
Requires-Dist: setuptools
Requires-Dist: senaite.lims (>=1.3.0)
Provides-Extra: test
Requires-Dist: Products.PloneTestCase ; extra == 'test'
Requires-Dist: plone.app.testing ; extra == 'test'
Requires-Dist: unittest2 ; extra == 'test'
